generic_configuration_builder/__init__.py
generic_configuration_builder/configuration_builder.py
generic_configuration_builder-1.2.2.dist-info/LICENSE
generic_configuration_builder-1.2.2.dist-info/WHEEL
generic_configuration_builder-1.2.2.dist-info/METADATA
generic_configuration_builder-1.2.2.dist-info/RECORD
