Metadata-Version: 2.1
Name: generic_configuration_builder
Version: 1.2.2
Summary: A simple library for parsing a configuration file format which is intended to build dependencies and hold parameters - well suited for experimentaton settings in which different experiments use different clases.
Keywords: configuration,config,experiment,dependencies,setup,parameters
Author-email: Sebastian Griesbach <sebastian.griesbach@zoho.eu>
Requires-Python: >=3.7
Classifier: Programming Language :: Python :: 3
Classifier: License :: OSI Approved :: MIT License
Classifier: Operating System :: OS Independent
Requires-Dist: configparser
Project-URL: Bug Tracker, https://github.com/Sebastian-Griesbach/Generic-Configuration-Builder/issues
Project-URL: Homepage, https://github.com/Sebastian-Griesbach/Generic-Configuration-Builder
